disambiguation_scripts/JED_Algorithms_public.py
disambiguation_scripts/JED_Back_Annotation_public.py
disambiguation_scripts/JED_Classes_public.py
disambiguation_scripts/JED_Cleaning_Functions_public.py
disambiguation_scripts/JED_Globals_public.py
disambiguation_scripts/JED_Helpers_public.py
disambiguation_scripts/JED_Main_public.py
disambiguation_scripts/JED_Pipelines_public.py
disambiguation_scripts/JED_Tag_New_Cases.py
disambiguation_scripts/JED_Update_Disambiguation_public.py
disambiguation_scripts/JED_Utilities_public.py
disambiguation_scripts/__init__.py
disambiguation_scripts/custom_tok.py
disambiguation_scripts/extract_new_cases.py
scales_nlp/__init__.py
scales_nlp/cli.py
scales_nlp/config.py
scales_nlp/datasets.py
scales_nlp/docket.py
scales_nlp/labels.py
scales_nlp/pipelines.py
scales_nlp/routines.py
scales_nlp/utils.py
scales_nlp/version.py
scales_nlp/data/courts.csv
scales_nlp/data/docket_examples.csv
scales_nlp-0.1.30.data/data/scales_nlp/courts.csv
scales_nlp-0.1.30.data/data/scales_nlp/docket_examples.csv
scales_nlp-0.1.30.data/data/scales_nlp_support/brmag_judges.csv
scales_nlp-0.1.30.data/data/scales_nlp_support/brmag_positions.csv
scales_nlp-0.1.30.data/data/scales_nlp_support/district_courts.csv
scales_nlp-0.1.30.data/data/scales_nlp_support/district_courts_94.csv
scales_nlp-0.1.30.data/data/scales_nlp_support/judge_demographics.csv
scales_nlp-0.1.30.data/data/scales_nlp_support/nature_suit.csv
scales_nlp-0.1.30.data/data/scales_nlp_support/statey2code.json
scales_nlp_support/__init__.py
scales_nlp_support/bundler.py
scales_nlp_support/core.py
scales_nlp_support/court_functions.py
scales_nlp_support/data_tools.py
scales_nlp_support/docket_entry_identification.py
scales_nlp_support/docket_functions.py
scales_nlp_support/entity_functions.py
scales_nlp_support/fhandle_tools.py
scales_nlp_support/fjc_functions.py
scales_nlp_support/language_tools.py
scales_nlp_support/lexicon.py
scales_nlp_support/mongo_connector.py
scales_nlp-0.1.30.dist-info/METADATA
scales_nlp-0.1.30.dist-info/WHEEL
scales_nlp-0.1.30.dist-info/entry_points.txt
scales_nlp-0.1.30.dist-info/top_level.txt
scales_nlp-0.1.30.dist-info/RECORD
