Metadata-Version: 2.1
Name: scales-nlp
Version: 0.1.30
Home-page: https://github.com/scales-okn/scales-nlp
Author: Nathan Dahlberg
Requires-Dist: cchardet ==2.2.0a2
Requires-Dist: configuration-maker
Requires-Dist: datasets
Requires-Dist: evaluate
Requires-Dist: flashtext
Requires-Dist: fuzzywuzzy
Requires-Dist: numpy
Requires-Dist: pacer-tools
Requires-Dist: pandas
Requires-Dist: pathlib
Requires-Dist: protobuf <3.21.0
Requires-Dist: sentencepiece
Requires-Dist: scikit-learn
Requires-Dist: spacy
Requires-Dist: toolz
Requires-Dist: torch
Requires-Dist: tqdm
Requires-Dist: transformers
